exx/__init__.py
exx/client.py
exx/exceptions.py
python_exx-0.0.2.dist-info/DESCRIPTION.rst
python_exx-0.0.2.dist-info/METADATA
python_exx-0.0.2.dist-info/RECORD
python_exx-0.0.2.dist-info/WHEEL
python_exx-0.0.2.dist-info/metadata.json
python_exx-0.0.2.dist-info/top_level.txt
